prodec/Descriptor.py
prodec/ProteinDescriptors.py
prodec/Transform.py
prodec/__init__.py
prodec/data.json
prodec/utils.py
prodec/version.py
prodec-1.0.2.post5.dist-info/LICENSE
prodec-1.0.2.post5.dist-info/METADATA
prodec-1.0.2.post5.dist-info/WHEEL
prodec-1.0.2.post5.dist-info/top_level.txt
prodec-1.0.2.post5.dist-info/RECORD
