Metadata-Version: 2.1
Name: prodec
Version: 1.0.2.post5
Summary: A package to calculate protein sequence descriptors
Home-page: https://github.com/OlivierBeq/ProDEC
Author: Olivier J. M. Béquignon
Author-email: "olivier.bequignon.maintainer@gmail.com"
Maintainer: Olivier J. M. Béquignon
Maintainer-email: "olivier.bequignon.maintainer@gmail.com"
License: MIT
Keywords: protein,descriptors,proteochemometrics,PCM,QSAR
Classifier: Development Status :: 5 - Production/Stable
Classifier: License :: OSI Approved :: MIT License
Classifier: Programming Language :: Python :: 3.9
Classifier: Programming Language :: Python :: 3.8
Classifier: Programming Language :: Python :: 3.7
Classifier: Programming Language :: Python :: 3.6
License-File: LICENSE
Requires-Dist: orjson
Requires-Dist: numpy
Requires-Dist: psutil
Requires-Dist: pandas
Provides-Extra: docs
Requires-Dist: sphinx ; extra == 'docs'
Requires-Dist: sphinx-rtd-theme ; extra == 'docs'
Requires-Dist: sphinx-autodoc-typehints ; extra == 'docs'
Provides-Extra: testing
Requires-Dist: pytest ; extra == 'testing'
